bimb/__init__.py
bimb/bimb.abi3.so
pybimb-0.2.1.dist-info/METADATA
pybimb-0.2.1.dist-info/WHEEL
pybimb-0.2.1.dist-info/licenses/LICENSE
pybimb-0.2.1.dist-info/RECORD
