Metadata-Version: 2.4
Name: pybimb
Version: 0.2.1
Classifier: Development Status :: 3 - Alpha
Classifier: Programming Language :: Python :: 3
Classifier: Programming Language :: Rust
Classifier: License :: OSI Approved :: MIT License
Classifier: Operating System :: OS Independent
Classifier: Intended Audience :: Developers
Classifier: Intended Audience :: Science/Research
Classifier: Topic :: Scientific/Engineering :: Artificial Intelligence
Classifier: Topic :: Software Development :: Libraries :: Python Modules
License-File: LICENSE
Summary: [WIP] A fast imageloader for PyTorch
Author-email: 7karni <7karni@proton.me>
Requires-Python: >=3.7
